ska_sdc2_scoring_utils/__init__.py
ska_sdc2_scoring_utils/__version__.py
ska_sdc2_scoring_utils/admin_api.py
ska_sdc2_scoring_utils/api_common.py
ska_sdc2_scoring_utils/logs.py
ska_sdc2_scoring_utils/sdc2_score.py
ska_sdc2_scoring_utils/sdc2_score_admin.py
ska_sdc2_scoring_utils/user_api.py
ska_sdc2_scoring_utils-1.0.0.dist-info/LICENSE
ska_sdc2_scoring_utils-1.0.0.dist-info/METADATA
ska_sdc2_scoring_utils-1.0.0.dist-info/WHEEL
ska_sdc2_scoring_utils-1.0.0.dist-info/entry_points.txt
ska_sdc2_scoring_utils-1.0.0.dist-info/top_level.txt
ska_sdc2_scoring_utils-1.0.0.dist-info/RECORD
