Metadata-Version: 2.1
Name: ska-sdc2-scoring-utils
Version: 1.0.0
Summary: Utility scripts for interacting with SKA SDC2 scoring service.
Home-page: https://gitlab.com/ska-telescope/sdc/sdc2-scoring-utils
Author: SKA Organisation
License: License :: OSI Approved :: BSD License
Platform: UNKNOWN
Classifier: Development Status :: 4 - Beta
Classifier: Programming Language :: Python :: 3
Classifier: License :: OSI Approved :: MIT License
Classifier: Operating System :: OS Independent
Classifier: Topic :: Scientific/Engineering :: Astronomy
Classifier: Intended Audience :: Developers
Classifier: Intended Audience :: Science/Research
Requires-Python: >=3.6
Requires-Dist: docopt
Requires-Dist: python-keycloak
Requires-Dist: requests
